piran/__init__.py
piran-0.1a0.dist-info/LICENSE.txt
piran-0.1a0.dist-info/METADATA
piran-0.1a0.dist-info/WHEEL
piran-0.1a0.dist-info/top_level.txt
piran-0.1a0.dist-info/RECORD
