Metadata-Version: 2.1
Name: piran
Version: 0.1a0
Summary: "Random" numbers based in pi's decimals
Home-page: https://github.com/Firefnix/PiRan
Author: Firefnix
License: LGPLv3
Project-URL: Bug Reports, https://github.com/Firefnix/PiRan/issues
Project-URL: Source, https://github.com/Firefnix/PiRan
Keywords: math pi random
Platform: UNKNOWN
Classifier: Development Status :: 3 - Alpha
Classifier: Intended Audience :: Developers
Classifier: Environment :: Console
Classifier: License :: OSI Approved :: GNU Lesser General Public License v3 or later (LGPLv3+)
Classifier: Programming Language :: Python :: 3
Classifier: Programming Language :: Python :: 3 :: Only
Requires-Python: >=3.5, <4
